download_manager/__init__.py
download_manager/_version.py
download_manager/cli.py
download_manager/download_manager.py
download_manager/process_manager.py
download_manager/utility.py
download_manager/database/__init__.py
download_manager/database/database_manager.py
download_manager/database/database_objects.py
download_manager/destination/__init__.py
download_manager/destination/writer.py
download_manager/progress/__init__.py
download_manager/progress/event.py
download_manager/progress/progress_factory.py
download_manager/progress/progress_manager.py
download_manager/progress/tdqm_progress_manager.py
download_manager/run/__init__.py
download_manager/run/trigger.py
download_manager/source/__init__.py
download_manager/source/source.py
download_manager/source/source_factory.py
download_manager/storage/__init__.py
download_manager/storage/storage_manager.py
download_manager-1.0.0b2.data/data/requirements.txt
download_manager-1.0.0b2.dist-info/METADATA
download_manager-1.0.0b2.dist-info/WHEEL
download_manager-1.0.0b2.dist-info/entry_points.txt
download_manager-1.0.0b2.dist-info/top_level.txt
download_manager-1.0.0b2.dist-info/RECORD
