Metadata-Version: 2.1
Name: download-manager
Version: 1.0.0b2
Summary: Download Manager
Home-page: https://gitlab.com/drb-python/tools/download-manager
Author: GAEL Systems
Author-email: drb-python@gael.fr
License: UNKNOWN
Project-URL: Source, https://gitlab.com/drb-python/tools/download-manager
Platform: UNKNOWN
Classifier: Programming Language :: Python :: 3.8
Classifier: License :: OSI Approved :: Apache Software License
Classifier: Operating System :: OS Independent
Requires-Python: >=3.8
Requires-Dist: drb (<1.1.0,>=1.0.1)
Requires-Dist: drb-impl-odata (<1.1.0,>=1.0.4)
Requires-Dist: requests (==2.27.1)
Requires-Dist: click (==8.0.3)
Requires-Dist: tenacity (==8.0.1)
Requires-Dist: tqdm (==4.63.0)
Requires-Dist: peewee (==3.14.10)
